magenta/__init__.py
magenta/version.py
magenta/common/__init__.py
magenta/common/beam_search.py
magenta/common/beam_search_test.py
magenta/common/concurrency.py
magenta/common/concurrency_test.py
magenta/common/nade.py
magenta/common/nade_test.py
magenta/common/sequence_example_lib.py
magenta/common/state_util.py
magenta/common/state_util_test.py
magenta/common/testing_lib.py
magenta/common/tf_utils.py
magenta/contrib/__init__.py
magenta/contrib/cudnn_rnn.py
magenta/contrib/rnn.py
magenta/contrib/rnn_test.py
magenta/contrib/seq2seq.py
magenta/contrib/seq2seq_test.py
magenta/contrib/training.py
magenta/interfaces/__init__.py
magenta/interfaces/midi/__init__.py
magenta/interfaces/midi/magenta_midi.py
magenta/interfaces/midi/midi_clock.py
magenta/interfaces/midi/midi_hub.py
magenta/interfaces/midi/midi_hub_test.py
magenta/interfaces/midi/midi_interaction.py
magenta/models/__init__.py
magenta/models/arbitrary_image_stylization/__init__.py
magenta/models/arbitrary_image_stylization/arbitrary_image_stylization_build_mobilenet_model.py
magenta/models/arbitrary_image_stylization/arbitrary_image_stylization_build_model.py
magenta/models/arbitrary_image_stylization/arbitrary_image_stylization_convert_tflite.py
magenta/models/arbitrary_image_stylization/arbitrary_image_stylization_distill_mobilenet.py
magenta/models/arbitrary_image_stylization/arbitrary_image_stylization_evaluate.py
magenta/models/arbitrary_image_stylization/arbitrary_image_stylization_losses.py
magenta/models/arbitrary_image_stylization/arbitrary_image_stylization_train.py
magenta/models/arbitrary_image_stylization/arbitrary_image_stylization_train_mobile.py
magenta/models/arbitrary_image_stylization/arbitrary_image_stylization_with_weights.py
magenta/models/arbitrary_image_stylization/export_hub.py
magenta/models/arbitrary_image_stylization/nza_model.py
magenta/models/coconet/__init__.py
magenta/models/coconet/coconet_evaluate.py
magenta/models/coconet/coconet_sample.py
magenta-2.1.4.dist-info/AUTHORS
magenta-2.1.4.dist-info/LICENSE
magenta-2.1.4.dist-info/METADATA
magenta-2.1.4.dist-info/WHEEL
magenta-2.1.4.dist-info/entry_points.txt
magenta-2.1.4.dist-info/top_level.txt
magenta-2.1.4.dist-info/RECORD
